miditoolkit/__init__.py
miditoolkit/constants.py
miditoolkit/midi/__init__.py
miditoolkit/midi/containers.py
miditoolkit/midi/parser.py
miditoolkit/midi/utils.py
miditoolkit/midi/examples_data/1390.mid
miditoolkit/pianoroll/__init__.py
miditoolkit/pianoroll/parser.py
miditoolkit/pianoroll/utils.py
miditoolkit/pianoroll/vis.py
miditoolkit-1.0.1.dist-info/METADATA
miditoolkit-1.0.1.dist-info/WHEEL
miditoolkit-1.0.1.dist-info/licenses/LICENSE
miditoolkit-1.0.1.dist-info/RECORD
