Metadata-Version: 2.1
Name: miditoolkit
Version: 1.0.1
Summary: A python package for working with MIDI data files.
Project-URL: Homepage, https://github.com/YatingMusic/miditoolkit
Author-email: wayne391 <s101062219@gmail.com>
License-Expression: MIT
License-File: LICENSE
Keywords: midi,mir,music
Classifier: Intended Audience :: Developers
Classifier: Intended Audience :: Science/Research
Classifier: License :: OSI Approved :: MIT License
Classifier: Operating System :: OS Independent
Classifier: Programming Language :: Python :: 3
Classifier: Programming Language :: Python :: 3.7
Classifier: Programming Language :: Python :: 3.8
Classifier: Programming Language :: Python :: 3.9
Classifier: Programming Language :: Python :: 3.10
Classifier: Topic :: Multimedia :: Sound/Audio :: MIDI
Requires-Python: >=3.7.0
Requires-Dist: matplotlib
Requires-Dist: mido>=1.1.16
Requires-Dist: numpy>=1.19
Provides-Extra: tests
Requires-Dist: pytest-cov; extra == 'tests'
Requires-Dist: pytest-xdist[psutil]; extra == 'tests'
